alot/__init__.py
alot/__main__.py
alot/account.py
alot/buffers.py
alot/completion.py
alot/crypto.py
alot/errors.py
alot/helper.py
alot/ui.py
alot/walker.py
alot/addressbook/__init__.py
alot/addressbook/abook.py
alot/addressbook/external.py
alot/commands/__init__.py
alot/commands/bufferlist.py
alot/commands/envelope.py
alot/commands/globals.py
alot/commands/search.py
alot/commands/taglist.py
alot/commands/thread.py
alot/commands/utils.py
alot/db/__init__.py
alot/db/attachment.py
alot/db/envelope.py
alot/db/errors.py
alot/db/manager.py
alot/db/message.py
alot/db/thread.py
alot/db/utils.py
alot/defaults/abook_contacts.spec
alot/defaults/alot.rc.spec
alot/defaults/default.bindings
alot/defaults/default.theme
alot/defaults/notmuch.rc.spec
alot/defaults/theme.spec
alot/settings/__init__.py
alot/settings/const.py
alot/settings/errors.py
alot/settings/manager.py
alot/settings/theme.py
alot/settings/utils.py
alot/utils/__init__.py
alot/utils/argparse.py
alot/utils/cached_property.py
alot/utils/configobj.py
alot/widgets/__init__.py
alot/widgets/bufferlist.py
alot/widgets/globals.py
alot/widgets/search.py
alot/widgets/thread.py
alot/widgets/utils.py
alot-0.7.0.dist-info/DESCRIPTION.rst
alot-0.7.0.dist-info/METADATA
alot-0.7.0.dist-info/RECORD
alot-0.7.0.dist-info/WHEEL
alot-0.7.0.dist-info/entry_points.txt
alot-0.7.0.dist-info/metadata.json
alot-0.7.0.dist-info/top_level.txt
