Metadata-Version: 2.0
Name: alot
Version: 0.7.0
Summary: Terminal MUA using notmuch mail
Home-page: https://github.com/pazz/alot
Author: Patrick Totzke
Author-email: patricktotzke@gmail.com
License: Copyright (C) 2012-18 Patrick Totzke
Platform: UNKNOWN
Classifier: Development Status :: 4 - Beta
Classifier: Environment :: Console :: Curses
Classifier: Framework :: Twisted
Classifier: Intended Audience :: End Users/Desktop
Classifier: License :: OSI Approved :: GNU General Public License v3 or later (GPLv3+)
Classifier: Operating System :: POSIX
Classifier: Programming Language :: Python :: 2.7
Classifier: Programming Language :: Python :: 2 :: Only
Classifier: Topic :: Communications :: Email :: Email Clients (MUA)
Classifier: Topic :: Database :: Front-Ends
Provides: alot
Requires-Python: >=2.7,<3.0
Requires-Dist: configobj (>=4.7.0)
Requires-Dist: gpg
Requires-Dist: notmuch (>=0.13)
Requires-Dist: python-magic
Requires-Dist: twisted (>=10.2.0)
Requires-Dist: urwid (>=1.3.0)
Requires-Dist: urwidtrees (>=1.0)
